classidgraph/__init__.py
classidgraph/directedgraph.py
classidgraph-0.6.1.dist-info/LICENSE
classidgraph-0.6.1.dist-info/METADATA
classidgraph-0.6.1.dist-info/WHEEL
classidgraph-0.6.1.dist-info/top_level.txt
classidgraph-0.6.1.dist-info/RECORD
